tox_gh/__init__.py
tox_gh/plugin.py
tox_gh/py.typed
tox_gh/version.py
tox_gh-1.6.1.dist-info/METADATA
tox_gh-1.6.1.dist-info/WHEEL
tox_gh-1.6.1.dist-info/entry_points.txt
tox_gh-1.6.1.dist-info/licenses/LICENSE
tox_gh-1.6.1.dist-info/RECORD
