Metadata-Version: 2.4
Name: tox-gh
Version: 1.6.1
Summary: Seamless integration of tox into GitHub Actions.
Project-URL: Documentation, https://github.com/tox-dev/tox-gh#tox-gh
Project-URL: Homepage, https://github.com/tox-dev/tox-gh
Project-URL: Source, https://github.com/tox-dev/tox-gh
Project-URL: Tracker, https://github.com/tox-dev/tox-gh/issues
Maintainer-email: Bernát Gábor <gaborjbernat@gmail.com>
License-Expression: MIT
License-File: LICENSE
Keywords: environments,isolated,testing,virtual
Classifier: Development Status :: 5 - Production/Stable
Classifier: Intended Audience :: Developers
Classifier: License :: OSI Approved :: MIT License
Classifier: Operating System :: OS Independent
Classifier: Programming Language :: Python
Classifier: Programming Language :: Python :: 3 :: Only
Classifier: Programming Language :: Python :: 3.10
Classifier: Programming Language :: Python :: 3.11
Classifier: Programming Language :: Python :: 3.12
Classifier: Programming Language :: Python :: 3.13
Classifier: Programming Language :: Python :: 3.14
Classifier: Topic :: Internet
Classifier: Topic :: Software Development :: Libraries
Classifier: Topic :: System
Requires-Python: >=3.10
Requires-Dist: tox>=4.31
Provides-Extra: testing
Requires-Dist: covdefaults>=2.3; extra == 'testing'
Requires-Dist: devpi-process>=1.0.2; extra == 'testing'
Requires-Dist: diff-cover>=9.7.1; extra == 'testing'
Requires-Dist: pytest-cov>=7; extra == 'testing'
Requires-Dist: pytest-mock>=3.15.1; extra == 'testing'
Requires-Dist: pytest>=8.4.2; extra == 'testing'
